{
    "menu": [
        {
            "name": "1. Achari Aaloo Kathi Roll",
            "price": 11.95,
            "link": null
        },
        {
            "name": "2. Paneer Tikka Kathi Roll",
            "price": 11.95,
            "link": null
        },
        {
            "name": "3. Mushroom Kathi Roll",
            "price": 11.95,
            "link": null
        },
        {
            "name": "4. Malai Paneer Kathi Roll",
            "price": 11.95,
            "link": null
        },
        {
            "name": "5. Egg Omelette Kathi Roll",
            "price": 11.95,
            "link": null
        },
        {
            "name": "6. Chicken Tikka Kathi Roll",
            "price": 11.95,
            "link": "https://www.yelp.com/menu/kathis-and-kababs-hicksville/item/6-chicken-tikka-kathi-roll"
        },
        {
            "name": "7. Chicken Malai Kathi Roll",
            "price": 11.95,
            "link": null
        },
        {
            "name": "8. Chicken Achari Kathi Roll",
            "price": 11.95,
            "link": null
        },
        {
            "name": "9. Chicken Seekh Kathi Roll",
            "price": 11.95,
            "link": "https://www.yelp.com/menu/kathis-and-kababs-hicksville/item/9-chicken-seekh-kathi-roll"
        },
        {
            "name": "10. Lamb Seekh Kathi Roll",
            "price": 14.95,
            "link": "https://www.yelp.com/menu/kathis-and-kababs-hicksville/item/10-lamb-seekh-kathi-roll"
        },
        {
            "name": "1. Vegetable Platter Kabab",
            "price": 14.95,
            "link": null
        },
        {
            "name": "2. Achari Aaloo Kabab",
            "price": 14.95,
            "link": null
        },
        {
            "name": "3. Paneer Tikka Kabab",
            "price": 14.95,
            "link": null
        },
        {
            "name": "4. Malai Paneer Tikka Kabab",
            "price": 14.95,
            "link": null
        },
        {
            "name": "5. Tandoori Mushroom Kabab",
            "price": 14.95,
            "link": null
        },
        {
            "name": "6. Chicken Tikka Kabab",
            "price": 14.95,
            "link": "https://www.yelp.com/menu/kathis-and-kababs-hicksville/item/6-chicken-tikka-kabab"
        },
        {
            "name": "7. Chicken Malai Tikka Kabab",
            "price": 14.95,
            "link": "https://www.yelp.com/menu/kathis-and-kababs-hicksville/item/7-chicken-malai-tikka-kabab"
        },
        {
            "name": "8. Chicken Achari Tikka Kabab",
            "price": 14.95,
            "link": null
        },
        {
            "name": "9. Chicken Seekh Kabab",
            "price": 14.95,
            "link": null
        },
        {
            "name": "10. Chicken Afghani Kabab",
            "price": 17.95,
            "link": null
        },
        {
            "name": "11. Tandoori Chicken Kabab",
            "price": 17.95,
            "link": null
        },
        {
            "name": "13. Lamb Seekh Kabab",
            "price": 19.95,
            "link": null
        },
        {
            "name": "14. Salmon Fish Tikka Kabab",
            "price": 21.95,
            "link": null
        },
        {
            "name": "15. Mutton Burra Kabab",
            "price": 26.95,
            "link": "https://www.yelp.com/menu/kathis-and-kababs-hicksville/item/15-mutton-burra-kabab"
        },
        {
            "name": "Paneer Achari Tikka",
            "price": 14.95,
            "link": null
        },
        {
            "name": "Tandoori Shrimp (8 pcs)",
            "price": 21.95,
            "link": null
        },
        {
            "name": "Tandoori Roti",
            "price": 2.95,
            "link": "https://www.yelp.com/menu/kathis-and-kababs-hicksville/item/tandoori-roti"
        },
        {
            "name": "Butter Naan",
            "price": 3.95,
            "link": null
        },
        {
            "name": "Garlic Naan",
            "price": 4.95,
            "link": "https://www.yelp.com/menu/kathis-and-kababs-hicksville/item/garlic-naan"
        },
        {
            "name": "Basmati Rice",
            "price": 5.95,
            "link": "https://www.yelp.com/menu/kathis-and-kababs-hicksville/item/basmati-rice"
        },
        {
            "name": "Dal Makhni (16 OZ)",
            "price": 11.95,
            "link": null
        },
        {
            "name": "Chana Masala (16 OZ)",
            "price": 11.95,
            "link": null
        },
        {
            "name": "Saag Paneer",
            "price": 11.95,
            "link": null
        },
        {
            "name": "Bottled Water",
            "price": 1.95,
            "link": null
        },
        {
            "name": "Soda",
            "price": 2.95,
            "link": null
        },
        {
            "name": "Indian Soda",
            "price": 3.95,
            "link": null
        },
        {
            "name": "Mango Lassi",
            "price": 5.95,
            "link": "https://www.yelp.com/menu/kathis-and-kababs-hicksville/item/mango-lassi"
        },
        {
            "name": "Achari Aloo Vegetarian Rice Bowl",
            "price": 12.95,
            "link": null
        },
        {
            "name": "Malai Paneer Vegetarian Rice Bowl",
            "price": 12.95,
            "link": null
        },
        {
            "name": "Paneer Tikka Vegetarian Rice Bowl",
            "price": 12.95,
            "link": null
        },
        {
            "name": "Chicken Tikka Rice Bowl",
            "price": 12.95,
            "link": null
        },
        {
            "name": "Chicken Malai Tikka Rice Bowl",
            "price": 12.95,
            "link": null
        },
        {
            "name": "Chicken Achari Rice Bowl",
            "price": 12.95,
            "link": null
        },
        {
            "name": "Lamb Seekh Kabab Rice Bowl",
            "price": 15.95,
            "link": null
        },
        {
            "name": "Masala Fries",
            "price": 6.95,
            "link": null
        },
        {
            "name": "Amritsari Fish",
            "price": 11.95,
            "link": null
        },
        {
            "name": "Chicken Momos",
            "price": 11.95,
            "link": "https://www.yelp.com/menu/kathis-and-kababs-hicksville/item/chicken-momos"
        },
        {
            "name": "Vegetable Momos",
            "price": 10.95,
            "link": "https://www.yelp.com/menu/kathis-and-kababs-hicksville/item/vegetable-momos"
        },
        {
            "name": "Chicken Wings",
            "price": 10.95,
            "link": null
        },
        {
            "name": "Vegetable Spring Roll",
            "price": 8.95,
            "link": null
        },
        {
            "name": "Chicken Spring Roll",
            "price": 9.95,
            "link": null
        },
        {
            "name": "Vegetable Momos",
            "price": 10.95,
            "link": "https://www.yelp.com/menu/kathis-and-kababs-hicksville/item/vegetable-momos-2"
        },
        {
            "name": "Gobhi Manchurian (Dry)",
            "price": 12.95,
            "link": "https://www.yelp.com/menu/kathis-and-kababs-hicksville/item/gobhi-manchurian-dry"
        },
        {
            "name": "Vegetable Manchurian- Dry (8pcs)",
            "price": 13.95,
            "link": null
        },
        {
            "name": "Chicken Manchurian- Dry (8 pcs)",
            "price": 14.95,
            "link": null
        },
        {
            "name": "Paneer Chilli - Dry",
            "price": 14.95,
            "link": null
        },
        {
            "name": "Chicken Chilli - Dry",
            "price": 14.95,
            "link": null
        },
        {
            "name": "Chicken Lollipop (6 pcs)",
            "price": 14.95,
            "link": null
        },
        {
            "name": "Chicken Drumsticks (6 pcs)",
            "price": 14.95,
            "link": null
        },
        {
            "name": "Gulab Jamun",
            "price": 5.95,
            "link": null
        },
        {
            "name": "Rasmalai",
            "price": 5.95,
            "link": null
        },
        {
            "name": "Kheer",
            "price": 5.95,
            "link": null
        }
    ]
}